{
  "type": "minecraft:crafting_shaped",
  "category": "misc",
  "key": {
    "+": {
      "item": "wandrous:tealestite_shard"
    },
    "-": {
      "item": "minecraft:string"
    },
    "x": {
      "tag": "c:glass_panes"
    }
  },
  "pattern": [
    " - ",
    "+x+",
    " - "
  ],
  "result": {
    "components": {
      "wandrous:glyph": {
        "a": 1.0,
        "b": 0.68,
        "g": 1.0,
        "glyph": "wandrous:weave",
        "id": "wandrous:weave",
        "r": 0.0
      }
    },
    "count": 1,
    "id": "wandrous:inscribed_lens"
  }
}